aoc_gliech/__init__.py
aoc_gliech/entrypoints.py
aoc_gliech/scripts.py
aoc_gliech/tofu/2023/01/main.tf
aoc_gliech/tofu/2023/06/main.tf
aoc_gliech/tofu/2023/06/modules/race/main.tf
aoc_gliech/tofu/modules/data/env.py
aoc_gliech/tofu/modules/data/inputs.tf
aoc_gliech/tofu/modules/data/main.tf
aoc_gliech/tofu/modules/data/outputs.tf
aoc_gliech/tofu/modules/data/versions.tf
aoc_gliech/y2015/d01.py
aoc_gliech/y2015/d02.py
aoc_gliech/y2023/__init__.py
aoc_gliech/y2023/d01.py
aoc_gliech/y2023/d02.py
aoc_gliech/y2023/d03.py
aoc_gliech/y2023/d04.py
aoc_gliech/y2023/d05.py
aoc_gliech/y2023/d06.py
aoc_gliech/y2023/d07.py
aoc_gliech/y2023/d08.py
aoc_gliech/y2023/d09.py
aoc_gliech/y2023/d10.py
aoc_gliech/y2023/d11.py
aoc_gliech/y2023/d15.py
aoc_gliech/y2024/d01.py
aoc_gliech/y2024/d02.py
aoc_gliech/y2024/d03.py
aoc_gliech/y2024/d04.py
aoc_gliech/y2024/d05.py
aoc_gliech/y2024/d06.py
aoc_gliech/y2025/d01.py
aoc_gliech/y2025/d01_extras.py
aoc_gliech/y2025/d02.py
aoc_gliech/y2025/d02_extras.py
aoc_gliech/y2025/d03.py
aoc_gliech/y2025/d03_extras.py
aoc_gliech/y2025/d04.py
aoc_gliech/y2025/d04_extras.py
aoc_gliech/y2025/d05.py
aoc_gliech/y2025/d06.py
aoc_gliech/y2025/d07.py
aoc_gliech/y2025/d07_extras.py
advent_of_code_gliech-0.3.0.dist-info/METADATA
advent_of_code_gliech-0.3.0.dist-info/WHEEL
advent_of_code_gliech-0.3.0.dist-info/entry_points.txt
advent_of_code_gliech-0.3.0.dist-info/licenses/LICENSE
advent_of_code_gliech-0.3.0.dist-info/RECORD
