Metadata-Version: 2.4
Name: advent-of-code-gliech
Version: 0.3.0
Summary: My solutions to https://adventofcode.com
Project-URL: homepage, https://github.com/gliech/advent-of-code
Author: gliech
License:                     GNU GENERAL PUBLIC LICENSE
License-File: LICENSE
Classifier: License :: OSI Approved :: GNU General Public License v3 (GPLv3)
Classifier: Operating System :: OS Independent
Classifier: Programming Language :: Python :: 3
Classifier: Topic :: Games/Entertainment :: Puzzle Games
Requires-Python: >=3.12
Requires-Dist: advent-of-code-data>=2.0.0
Requires-Dist: browser-cookie3>=0.19.1
Requires-Dist: docopt-ng>=0.9.0
Requires-Dist: numpy>=1.26.2
Requires-Dist: prettyprinter>=0.18.0
Requires-Dist: pyyaml>=6.0.1
Requires-Dist: scipy>=1.14.1
